[{"Stevnenummer":"15090","Navn":"Kevin Nilsen Lillefoss","Arrangør":"Dokka PK","Dato":"31.05.2026","Type":"1M2","Resultat":"42","InrX":"9","Klasse":"A","Respit":"","Med Respit":"","Vinnersum":"91","Prosent":"46,15%"},{"Stevnenummer":"15090","Navn":"Mats Andre Lian Arntsen","Arrangør":"Dokka PK","Dato":"31.05.2026","Type":"1M","Resultat":"95","InrX":"33","Klasse":"B","Respit":"","Med Respit":"","Vinnersum":"109","Prosent":"87,16%"},{"Stevnenummer":"15090","Navn":"Kjell Atle Lund","Arrangør":"Dokka PK","Dato":"31.05.2026","Type":"1R","Resultat":"88","InrX":"27","Klasse":"B","Respit":"","Med Respit":"","Vinnersum":"113","Prosent":"77,88%"},{"Stevnenummer":"15090","Navn":"Kevin Nilsen Lillefoss","Arrangør":"Dokka PK","Dato":"31.05.2026","Type":"1R","Resultat":"92","InrX":"23","Klasse":"D","Respit":"","Med Respit":"","Vinnersum":"113","Prosent":"81,42%"},{"Stevnenummer":"15090","Navn":"Marius Kristoffer Nilsen","Arrangør":"Dokka PK","Dato":"31.05.2026","Type":"1R","Resultat":"86","InrX":"21","Klasse":"D","Respit":"","Med Respit":"","Vinnersum":"113","Prosent":"76,11%"},{"Stevnenummer":"15090","Navn":"Mats Andre Lian Arntsen","Arrangør":"Dokka PK","Dato":"31.05.2026","Type":"1RR","Resultat":"109","InrX":"47","Klasse":"Å","Respit":"","Med Respit":"","Vinnersum":"109","Prosent":"100,00%"},{"Stevnenummer":"15090","Navn":"Kjell Atle Lund","Arrangør":"Dokka PK","Dato":"31.05.2026","Type":"1SP","Resultat":"86","InrX":"23","Klasse":"A","Respit":"","Med Respit":"","Vinnersum":"97","Prosent":"88,66%"},{"Stevnenummer":"202606051","Navn":"Mats Andre Lian Arntsen","Arrangør":"Bodung PK","Dato":"05.06.2026","Type":"6F","Resultat":"553","InrX":"8","Klasse":"B","Respit":"15","Med Respit":"568","Vinnersum":"","Prosent":""},{"Stevnenummer":"202606051","Navn":"Marius Kristoffer Nilsen","Arrangør":"Bodung PK","Dato":"05.06.2026","Type":"6F","Resultat":"543","InrX":"7","Klasse":"B","Respit":"15","Med Respit":"558","Vinnersum":"","Prosent":""},{"Stevnenummer":"202606051","Navn":"Svetlana Halnes","Arrangør":"Bodung PK","Dato":"05.06.2026","Type":"6F","Resultat":"482","InrX":"7","Klasse":"D","Respit":"75","Med Respit":"557","Vinnersum":"","Prosent":""},{"Stevnenummer":"202606051","Navn":"Steinar Andreas Glader","Arrangør":"Bodung PK","Dato":"05.06.2026","Type":"6F","Resultat":"477","InrX":"1","Klasse":"C","Respit":"45","Med Respit":"522","Vinnersum":"","Prosent":""},{"Stevnenummer":"202606051","Navn":"Arne Kristian Stensby","Arrangør":"Bodung PK","Dato":"05.06.2026","Type":"6F","Resultat":"465","InrX":"1","Klasse":"D","Respit":"75","Med Respit":"540","Vinnersum":"","Prosent":""},{"Stevnenummer":"202606051","Navn":"Bartosz Sierakowski","Arrangør":"Bodung PK","Dato":"05.06.2026","Type":"6F","Resultat":"456","InrX":"4","Klasse":"D","Respit":"75","Med Respit":"531","Vinnersum":"","Prosent":""},{"Stevnenummer":"202606051","Navn":"Viljar Nymoen","Arrangør":"Bodung PK","Dato":"05.06.2026","Type":"6F","Resultat":"451","InrX":"2","Klasse":"D","Respit":"75","Med Respit":"526","Vinnersum":"","Prosent":""},{"Stevnenummer":"202606051","Navn":"Kent Henning Skoglund","Arrangør":"Bodung PK","Dato":"05.06.2026","Type":"6F","Resultat":"448","InrX":"1","Klasse":"D","Respit":"75","Med Respit":"523","Vinnersum":"","Prosent":""},{"Stevnenummer":"202606051","Navn":"Jessica Alvero Sandnes","Arrangør":"Bodung PK","Dato":"05.06.2026","Type":"6F","Resultat":"447","InrX":"3","Klasse":"D","Respit":"75","Med Respit":"522","Vinnersum":"","Prosent":""},{"Stevnenummer":"202606051","Navn":"Øystein Thorbjørnsen","Arrangør":"Bodung PK","Dato":"05.06.2026","Type":"6F","Resultat":"265","InrX":"0","Klasse":"D","Respit":"75","Med Respit":"340","Vinnersum":"","Prosent":""},{"Stevnenummer":"15904","Navn":"Arne Kristian Stensby","Arrangør":"Aron SK","Dato":"07.06.2026","Type":"1F","Resultat":"83","InrX":"20","Klasse":"C","Respit":"","Med Respit":"","Vinnersum":"109","Prosent":"76,15%"},{"Stevnenummer":"15904","Navn":"Arne Kristian Stensby","Arrangør":"Aron SK","Dato":"07.06.2026","Type":"1M","Resultat":"63","InrX":"9","Klasse":"C","Respit":"","Med Respit":"","Vinnersum":"110","Prosent":"57,27%"},{"Stevnenummer":"15904","Navn":"Mats Andre Lian Arntsen","Arrangør":"Aron SK","Dato":"07.06.2026","Type":"1M1","Resultat":"86","InrX":"15","Klasse":"A","Respit":"","Med Respit":"","Vinnersum":"97","Prosent":"88,66%"},{"Stevnenummer":"15904","Navn":"Marius Kristoffer Nilsen","Arrangør":"Aron SK","Dato":"07.06.2026","Type":"1M1","Resultat":"70","InrX":"10","Klasse":"A","Respit":"","Med Respit":"","Vinnersum":"97","Prosent":"72,16%"},{"Stevnenummer":"15904","Navn":"Steinar Andreas Glader","Arrangør":"Aron SK","Dato":"07.06.2026","Type":"1M1","Resultat":"59","InrX":"8","Klasse":"A","Respit":"","Med Respit":"","Vinnersum":"97","Prosent":"60,82%"},{"Stevnenummer":"15904","Navn":"Kevin Nilsen Lillefoss","Arrangør":"Aron SK","Dato":"07.06.2026","Type":"1M1","Resultat":"54","InrX":"4","Klasse":"A","Respit":"","Med Respit":"","Vinnersum":"97","Prosent":"55,67%"},{"Stevnenummer":"15904","Navn":"Steinar Andreas Glader","Arrangør":"Aron SK","Dato":"07.06.2026","Type":"1M2","Resultat":"78","InrX":"19","Klasse":"A","Respit":"","Med Respit":"","Vinnersum":"91","Prosent":"85,71%"},{"Stevnenummer":"15904","Navn":"Marius Kristoffer Nilsen","Arrangør":"Aron SK","Dato":"07.06.2026","Type":"1M2","Resultat":"68","InrX":"11","Klasse":"A","Respit":"","Med Respit":"","Vinnersum":"91","Prosent":"74,73%"},{"Stevnenummer":"15904","Navn":"Kevin Nilsen Lillefoss","Arrangør":"Aron SK","Dato":"07.06.2026","Type":"1M2","Resultat":"37","InrX":"4","Klasse":"A","Respit":"","Med Respit":"","Vinnersum":"91","Prosent":"40,66%"},{"Stevnenummer":"15904","Navn":"Mats Andre Lian Arntsen","Arrangør":"Aron SK","Dato":"07.06.2026","Type":"1RR","Resultat":"103","InrX":"26","Klasse":"Å","Respit":"","Med Respit":"","Vinnersum":"106","Prosent":"97,17%"},{"Stevnenummer":"202606101","Navn":"Marius Kristoffer Nilsen","Arrangør":"Bodung PK","Dato":"10.06.2026","Type":"5","Resultat":"527","InrX":"6","Klasse":"B","Respit":"15","Med Respit":"542","Vinnersum":"","Prosent":""},{"Stevnenummer":"202606101","Navn":"Mats Andre Lian Arntsen","Arrangør":"Bodung PK","Dato":"10.06.2026","Type":"5","Resultat":"499","InrX":"6","Klasse":"B","Respit":"15","Med Respit":"514","Vinnersum":"","Prosent":""},{"Stevnenummer":"202606101","Navn":"Svetlana Halnes","Arrangør":"Bodung PK","Dato":"10.06.2026","Type":"5","Resultat":"465","InrX":"1","Klasse":"D","Respit":"75","Med Respit":"540","Vinnersum":"","Prosent":""},{"Stevnenummer":"202606101","Navn":"Arne Kristian Stensby","Arrangør":"Bodung PK","Dato":"10.06.2026","Type":"5","Resultat":"446","InrX":"1","Klasse":"D","Respit":"75","Med Respit":"521","Vinnersum":"","Prosent":""},{"Stevnenummer":"202606101","Navn":"Kent Henning Skoglund","Arrangør":"Bodung PK","Dato":"10.06.2026","Type":"5","Resultat":"418","InrX":"3","Klasse":"D","Respit":"75","Med Respit":"493","Vinnersum":"","Prosent":""},{"Stevnenummer":"202606101","Navn":"Pernille Veronica Moss Nystuen","Arrangør":"Bodung PK","Dato":"10.06.2026","Type":"5","Resultat":"303","InrX":"3","Klasse":"D","Respit":"75","Med Respit":"378","Vinnersum":"","Prosent":""},{"Stevnenummer":"202606101","Navn":"Arve Grimsmo","Arrangør":"Bodung PK","Dato":"10.06.2026","Type":"5","Resultat":"240","InrX":"1","Klasse":"D","Respit":"75","Med Respit":"315","Vinnersum":"","Prosent":""},{"Stevnenummer":"202606101","Navn":"Aleksander Becker Birkeland","Arrangør":"Bodung PK","Dato":"10.06.2026","Type":"5","Resultat":"220","InrX":"0","Klasse":"D","Respit":"75","Med Respit":"295","Vinnersum":"","Prosent":""},{"Stevnenummer":"202606102","Navn":"Mats Andre Lian Arntsen","Arrangør":"Bodung PK","Dato":"10.06.2026","Type":"5","Resultat":"509","InrX":"6","Klasse":"B","Respit":"15","Med Respit":"524","Vinnersum":"","Prosent":""},{"Stevnenummer":"202606102","Navn":"Kent Henning Skoglund","Arrangør":"Bodung PK","Dato":"10.06.2026","Type":"5","Resultat":"380","InrX":"1","Klasse":"D","Respit":"75","Med Respit":"455","Vinnersum":"","Prosent":""},{"Stevnenummer":"202606103","Navn":"Marius Kristoffer Nilsen","Arrangør":"Bodung PK","Dato":"10.06.2026","Type":"8F","Resultat":"279","InrX":"7","Klasse":"","Respit":"","Med Respit":"","Vinnersum":"","Prosent":""},{"Stevnenummer":"202606103","Navn":"Mats Andre Lian Arntsen","Arrangør":"Bodung PK","Dato":"10.06.2026","Type":"8F","Resultat":"271","InrX":"4","Klasse":"","Respit":"","Med Respit":"","Vinnersum":"","Prosent":""},{"Stevnenummer":"202606103","Navn":"Arne Kristian Stensby","Arrangør":"Bodung PK","Dato":"10.06.2026","Type":"8F","Resultat":"262","InrX":"4","Klasse":"","Respit":"","Med Respit":"","Vinnersum":"","Prosent":""},{"Stevnenummer":"202606103","Navn":"Aleksander Becker Birkeland","Arrangør":"Bodung PK","Dato":"10.06.2026","Type":"8F","Resultat":"192","InrX":"0","Klasse":"","Respit":"","Med Respit":"","Vinnersum":"","Prosent":""},{"Stevnenummer":"202606103","Navn":"Pernille Veronica Moss Nystuen","Arrangør":"Bodung PK","Dato":"10.06.2026","Type":"8F","Resultat":"158","InrX":"1","Klasse":"","Respit":"","Med Respit":"","Vinnersum":"","Prosent":""},{"Stevnenummer":"202606104","Navn":"Mats Andre Lian Arntsen","Arrangør":"Bodung PK","Dato":"10.06.2026","Type":"8F","Resultat":"292","InrX":"10","Klasse":"","Respit":"","Med Respit":"","Vinnersum":"","Prosent":""},{"Stevnenummer":"202606104","Navn":"Arne Kristian Stensby","Arrangør":"Bodung PK","Dato":"10.06.2026","Type":"8F","Resultat":"247","InrX":"2","Klasse":"","Respit":"","Med Respit":"","Vinnersum":"","Prosent":""}]